[
    {
        "Старший программист-разработчик (Python/Django) / Senior back-end developer": {
            "Название компании": "CATAPULTO.RU",
            "Город": "Москва",
            "Зарплата": "от 200 000 до 300 000 руб. на руки",
            "Ссылка": "https://spb.hh.ru/vacancy/80002041?from=vacancy_search_list&query=python"
        }
    },
    {
        "Младший специалист отдела разработки (Python) / Специалист по парсингу данных": {
            "Название компании": "MillionAgents",
            "Город": "Москва",
            "Зарплата": "до 70 000 руб. на руки",
            "Ссылка": "https://spb.hh.ru/vacancy/81639879?from=vacancy_search_list&query=python"
        }
    },
    {
        "Middle Разработчик Python (Backend)": {
            "Название компании": "ООО Корпорация ЗНАК",
            "Город": "Москва",
            "Зарплата": "от 180 000 до 240 000 руб. на руки",
            "Ссылка": "https://spb.hh.ru/vacancy/81974265?from=vacancy_search_list&query=python"
        }
    },
    {
        "Middle+ Python Developer (backend)": {
            "Название компании": "ООО Агент Умный полис",
            "Город": "Санкт-Петербург",
            "Зарплата": "от 250 000 до 300 000 руб. на руки",
            "Ссылка": "https://spb.hh.ru/vacancy/81587055?from=vacancy_search_list&query=python"
        }
    },
    {
        "Middle Python-разработчик": {
            "Название компании": "AERODISK",
            "Город": "Москва",
            "Зарплата": "от 140 000 до 250 000 руб. на руки",
            "Ссылка": "https://spb.hh.ru/vacancy/82040028?from=vacancy_search_list&query=python"
        }
    },
    {
        "Программист Python": {
            "Название компании": "БО-ЭНЕРГО",
            "Город": "Москва",
            "Зарплата": "до 130 000 руб. на руки",
            "Ссылка": "https://spb.hh.ru/vacancy/82039618?from=vacancy_search_list&query=python"
        }
    }
]